LICENSE
MANIFEST.in
README.md
pyproject.toml
setup.py
categorical_mix/__init__.py
categorical_mix/categorical_mix.py
categorical_mix.egg-info/PKG-INFO
categorical_mix.egg-info/SOURCES.txt
categorical_mix.egg-info/dependency_links.txt
categorical_mix.egg-info/requires.txt
categorical_mix.egg-info/top_level.txt
categorical_mix/constants/__init__.py
categorical_mix/constants/constants.py
categorical_mix/ext/__init__.py
categorical_mix/ext/catmix_cpp_ext.cpp
categorical_mix/ext/catmix_utilities.cpp
categorical_mix/ext/catmix_utilities.h
categorical_mix/ext/responsibility_calcs.cpp
categorical_mix/ext/responsibility_calcs.h
categorical_mix/ext/weight_updates.cpp
categorical_mix/ext/weight_updates.h
categorical_mix/ext/.vscode/settings.json
categorical_mix/utilities/__init__.py
categorical_mix/utilities/catmix_utilities.py
categorical_mix/utilities/special_functions.py
docs/conf.py
tests/__init__.py
tests/test_cpp_extension.py
tests/test_exception_handling.py
tests/test_fitting.py
tests/test_data/converted_seqs.txt.gz
tests/test_data/decoys.npy
tests/test_data/encoded_test_data.npy