Metadata-Version: 2.1
Name: categorical_mix
Version: 0.2.0.0
Summary: A package for fitting simple categorical mixture models to sequence data
Author-email: Jonathan Parkinson <jlparkinson1@gmail.com>
License: MIT License
Project-URL: Homepage, https://github.com/jlparki/categorical_mixture
Project-URL: respository, https://github.com/jlparki/categorical_mixture
Keywords: categorical mixture,mixture model
Requires-Python: >=3.7
License-File: LICENSE
Requires-Dist: setuptools
Requires-Dist: wheel
Requires-Dist: pybind11>=2.4
Requires-Dist: numpy
